{
    "canonical": {
        "id": "ibm-nwsc",
        "src": "scancode-licensedb"
    },
    "aliases": {
        "custom": [
            "IBM International Licence Agreement for Non-Warranted Sample Code",
            "IBM Non-Warranted Sample Code Licence"
        ],
        "scancodeLicensedb": [
            "IBM International License Agreement for Non-Warranted Sample Code",
            "IBM Non-Warranted Sample Code License",
            "LicenseRef-scancode-ibm-nwsc"
        ]
    },
    "rejected": [],
    "risky": []
}
