{
    "canonical": {
        "id": "qt-commercial-1.1",
        "src": "scancode-licensedb"
    },
    "aliases": {
        "custom": [
            "Qt Commercial Licence v1.1",
            "Qt for Application Development Licence Agreement v1.1"
        ],
        "scancodeLicensedb": [
            "LicenseRef-scancode-qt-commercial-1.1",
            "Qt Commercial License v1.1",
            "Qt for Application Development License Agreement v1.1"
        ]
    },
    "rejected": [],
    "risky": [],
    "isMajorVersionOnly": true
}
